Test69420/__init__.py
Test69420/test.py
Test69420-0.0.2.dist-info/METADATA
Test69420-0.0.2.dist-info/WHEEL
Test69420-0.0.2.dist-info/top_level.txt
Test69420-0.0.2.dist-info/RECORD
